uncloud/cli.py
uncloud_backup-0.1.1.dist-info/METADATA
uncloud_backup-0.1.1.dist-info/WHEEL
uncloud_backup-0.1.1.dist-info/entry_points.txt
uncloud_backup-0.1.1.dist-info/licenses/LICENSE
uncloud_backup-0.1.1.dist-info/RECORD
