Metadata-Version: 2.4
Name: uncloud-backup
Version: 0.1.1
Summary: Local backups of your cloudy data.
License-File: LICENSE
Requires-Python: >=3.12
Requires-Dist: click>=8.3.0
